ginger/__init__.py
ginger/libginger.py
ginger/libtreebank.py
ginger/libtreerender.py
ginger/main.py
gingertree-0.15.0.dist-info/LICENSE.md
gingertree-0.15.0.dist-info/METADATA
gingertree-0.15.0.dist-info/WHEEL
gingertree-0.15.0.dist-info/entry_points.txt
gingertree-0.15.0.dist-info/top_level.txt
gingertree-0.15.0.dist-info/RECORD
