Metadata-Version: 2.1
Name: gingertree
Version: 0.15.0
Summary: Format conversion and graphical representation of [Universal Dependencies](http://universaldependencies.org) trees.
Home-page: https://github.com/LoicGrobol/ginger
Author-email: Loïc Grobol <loic.grobol@gmail.com>
License: MIT
Project-URL: Homepage, https://github.com/LoicGrobol/ginger
Keywords: nlp,syntax,universal dependencies
Platform: UNKNOWN
Requires-Python: >=3.8
License-File: LICENSE.md
Requires-Dist: click (>=8.0.4)
Provides-Extra: images
Requires-Dist: pycairo (>=1.15.10) ; extra == 'images'
